locomotion/__init__.py
locomotion/animal.py
locomotion/heatmap.py
locomotion/trajectory.py
locomotion/write.py
locomotion-1.0.0.dist-info/LICENSE.md
locomotion-1.0.0.dist-info/METADATA
locomotion-1.0.0.dist-info/WHEEL
locomotion-1.0.0.dist-info/top_level.txt
locomotion-1.0.0.dist-info/RECORD
