Metadata-Version: 2.1
Name: locomotion
Version: 1.0.0
Summary: Computational geometric tools for quantitative comparison of locomotory behavior
Home-page: https://github.com/mechunderlyingbehavior/locomotion
Author: Mechanisms Underlying Behavior Lab
Author-email: mechunderlyingbehavior@gmail.com
License: MIT
Project-URL: Lab Website, https://https://mechunderlyingbehavior.wordpress.com/
Platform: UNKNOWN
Classifier: License :: OSI Approved :: MIT License
Classifier: Programming Language :: Python :: 3.7
Requires-Dist: numpy (>=1.16.2)
Requires-Dist: plotly (>=4.4.1)
Requires-Dist: scipy (>=1.2.1)
Requires-Dist: dtw-python (>=1.1.4)
